Notion2Pelican/Notion2Pelican.py
Notion2Pelican/__init__.py
Notion2Pelican/notion2md.py
Notion2Pelican-0.0.4.dist-info/LICENSE
Notion2Pelican-0.0.4.dist-info/METADATA
Notion2Pelican-0.0.4.dist-info/WHEEL
Notion2Pelican-0.0.4.dist-info/top_level.txt
Notion2Pelican-0.0.4.dist-info/RECORD
