Metadata-Version: 2.1
Name: Notion2Pelican
Version: 0.0.4
Summary: Import notion pages in pelican blogging format
Home-page: https://github.com/oberron/Notion2Pelican
Author: oberron
Author-email: one.annum@gmail.com
License: LICENSE
Project-URL: Bug Tracker, https://github.com/oberron/Notion2Pelican/issues
Keywords: Notion Pelican
Classifier: Development Status :: 3 - Alpha
Classifier: Topic :: Utilities
Classifier: License :: OSI Approved :: MIT License
Classifier: Environment :: Console
Classifier: Intended Audience :: End Users/Desktop
Classifier: Intended Audience :: Developers
Classifier: Operating System :: OS Independent
Classifier: Programming Language :: Python :: 3.8
Classifier: Programming Language :: Python :: 3.9
Classifier: Programming Language :: Python :: 3.10
Classifier: Programming Language :: Python :: 3.11
Classifier: Topic :: Utilities
Requires-Python: >=3.8
License-File: LICENSE
Requires-Dist: requests
Provides-Extra: dev
Requires-Dist: coverage ; extra == 'dev'
Requires-Dist: darglint ; extra == 'dev'
Requires-Dist: python-dotenv ; extra == 'dev'
Requires-Dist: flake8 ; extra == 'dev'
Requires-Dist: Markdown ; extra == 'dev'
Requires-Dist: pyroma ; extra == 'dev'
Requires-Dist: pelican ; extra == 'dev'
Requires-Dist: pytest ; extra == 'dev'
Requires-Dist: recommonmark ; extra == 'dev'
Requires-Dist: sphinx ; extra == 'dev'
Requires-Dist: sphinx-markdown-builder ; extra == 'dev'
Requires-Dist: sphinx-rtd-theme ; extra == 'dev'
Requires-Dist: tox ; extra == 'dev'
Requires-Dist: twine ; extra == 'dev'
Requires-Dist: wheel ; extra == 'dev'
